{
    "title": "Carte Zelda",
    "description": "Une carte magnifiquement conçue arborant avec élégance le logo emblématique de Zelda.",
    "details": "Sur cette carte captivante, se dévoile à nos yeux émerveillés le prestigieux logo du célèbre jeu Zelda. Placé au cœur de l'ensemble, ce logo occupe une position centrale qui en fait l'élément indispensable et saisissant de cette composition cartographique.",
    "sizes": {
        "largeur": 11,
        "longueur": 15.5,
        "profondeur": ""
    },
    "category": "Carte",
    "tag": "",
    "price": 9,
    "images": [
        "https://i.ibb.co/P6S62KD/second1.png",
        "https://i.ibb.co/pKmTx0x/main1-8.png",
        "https://i.ibb.co/n6tXKP4/main2-4.png"
    ]
}
